xia_login_flask/__init__.py
xia_login_flask/account.cp310-win_amd64.pyd
xia_login_flask-0.2.11.dist-info/LICENSE.txt
xia_login_flask-0.2.11.dist-info/METADATA
xia_login_flask-0.2.11.dist-info/WHEEL
xia_login_flask-0.2.11.dist-info/top_level.txt
xia_login_flask-0.2.11.dist-info/RECORD
